mcbase64x32/__init__.py
mcbase64x32/main.py
mcbase64x32/utils/baseList.json
mcbase64x32-1.0.0.dist-info/METADATA
mcbase64x32-1.0.0.dist-info/WHEEL
mcbase64x32-1.0.0.dist-info/entry_points.txt
mcbase64x32-1.0.0.dist-info/licenses/LICENSE
mcbase64x32-1.0.0.dist-info/RECORD
