Metadata-Version: 2.4
Name: mcbase64x32
Version: 1.0.0
Summary: A high-performance Base64x32 implementation specialized for maximizing data storage in Minecraft books using numpy vectorized operations.
Author: ThorTuwy, victordlp8
License-File: LICENSE
Requires-Python: >=3.13
Requires-Dist: numpy>=2.3.2
